tuberd-0.18.3.dist-info/RECORD
tuberd-0.18.3.dist-info/WHEEL
tuberd-0.18.3.dist-info/entry_points.txt
tuberd-0.18.3.dist-info/top_level.txt
tuberd-0.18.3.dist-info/METADATA
tuberd-0.18.3.dist-info/licenses/LICENSE
tuber/server.py
tuber/_version.py
tuber/client.py
tuber/codecs.py
tuber/__init__.py
tuber/_tuber_runtime.cpython-312-darwin.so
tuber/schema.py
tuber/include/tuber_support.hpp
tuber/tests/conftest.py
tuber/tests/test_module.cpp
tuber/tests/__init__.py
tuber/tests/test.py
tuber/tests/test_module.cpython-312-darwin.so
