Metadata-Version: 2.4
Name: tuberd
Version: 0.18.3
Summary: Serve Python (or C++) objects across a LAN using something like JSON-RPC
Author-email: Graeme Smecher <gsmecher@threespeedlogic.com>
License-Expression: BSD-3-Clause
Project-URL: source, https://github.com/gsmecher/tuberd
Classifier: Programming Language :: Python :: 3
Classifier: Operating System :: OS Independent
License-File: LICENSE
Provides-Extra: client
Requires-Dist: requests; extra == "client"
Requires-Dist: requests-futures; extra == "client"
Provides-Extra: async
Requires-Dist: aiohttp; extra == "async"
Requires-Dist: requests; extra == "async"
Requires-Dist: requests-futures; extra == "async"
Provides-Extra: cbor
Requires-Dist: cbor2; extra == "cbor"
Provides-Extra: numpy
Requires-Dist: numpy; extra == "numpy"
Provides-Extra: orjson
Requires-Dist: orjson; extra == "orjson"
Provides-Extra: dev
Requires-Dist: aiohttp; extra == "dev"
Requires-Dist: cbor2; extra == "dev"
Requires-Dist: jsonschema; extra == "dev"
Requires-Dist: numpy; extra == "dev"
Requires-Dist: orjson; extra == "dev"
Requires-Dist: pytest; extra == "dev"
Requires-Dist: pytest-asyncio; extra == "dev"
Requires-Dist: requests; extra == "dev"
Requires-Dist: requests-futures; extra == "dev"
Dynamic: license-file
